src/txtad/__init__.py
src/txtad/load_json.py
src/txtad/room_example.py
src/txtad/run.py
src/txtad/structures.py
structured_text_adventure_engine-0.0.1.dist-info/METADATA
structured_text_adventure_engine-0.0.1.dist-info/WHEEL
structured_text_adventure_engine-0.0.1.dist-info/licenses/LICENCE
structured_text_adventure_engine-0.0.1.dist-info/RECORD
