Metadata-Version: 2.1
Name: structured-text-adventure-engine
Version: 0.0.1
Summary: A package made to handle old-style text adventures.
Project-URL: Homepage, https://github.com/jumpingtj/python-structured-text-adventures/
Project-URL: Bug Tracker, https://github.com/jumpingtj/python-structured-text-adventures/issues
Author: Toby Swinson-howell
License-File: LICENCE
Classifier: License :: OSI Approved :: MIT License
Classifier: Operating System :: OS Independent
Classifier: Programming Language :: Python :: 3
Requires-Python: >=3.7
